romanian_embeddings/__init__.py
romanian_embeddings/utils_model.py
romanian_embeddings-0.4.dist-info/METADATA
romanian_embeddings-0.4.dist-info/WHEEL
romanian_embeddings-0.4.dist-info/top_level.txt
romanian_embeddings-0.4.dist-info/RECORD
