Metadata-Version: 2.1
Name: romanian-embeddings
Version: 0.4
Summary: Romanian language embeddings using transformers and ONNX.
Home-page: UNKNOWN
Author: Mihai Ilie
Author-email: ilie.mihai92@gmail.com
License: UNKNOWN
Keywords: nlp transformers onnx romanian embeddings
Platform: UNKNOWN
Requires-Dist: numpy
Requires-Dist: onnxruntime
Requires-Dist: transformers
